pepe_qrcode_cli/__init__.py
pepe_qrcode_cli/__main__.py
pepe_qrcode_cli/main.py
pepe_qrcode_cli/neokararararar.png
pepe_qrcode_cli-0.4.0.dist-info/entry_points.txt
pepe_qrcode_cli-0.4.0.dist-info/WHEEL
pepe_qrcode_cli-0.4.0.dist-info/METADATA
pepe_qrcode_cli-0.4.0.dist-info/RECORD
