Metadata-Version: 2.1
Name: pepe-qrcode-cli
Version: 0.4.0
Summary: QRCode CLI for generating simple QR codes
Author: Pepe
Author-email: pimanroya06@gmail.com
Requires-Python: >=3.7,<4.0
Classifier: Programming Language :: Python :: 3
Classifier: Programming Language :: Python :: 3.10
Classifier: Programming Language :: Python :: 3.7
Classifier: Programming Language :: Python :: 3.8
Classifier: Programming Language :: Python :: 3.9
Requires-Dist: Pillow (>=9.0.0,<10.0.0)
Requires-Dist: pyzbar (>=0.1.8,<0.2.0)
Requires-Dist: qrcode (>=7.3.1,<8.0.0)
Requires-Dist: typer[all] (>=0.4.0,<0.5.0)
